.gitignore
CHANGELOG.md
COPYING
README.md
build-appimage.sh
cdtray
linuxdeploy-plugin-conda.sh
requirements.txt
screenshot.jpg
setup.cfg
setup.py
.github/workflows/main.yml
CDTray/Cddb.py
CDTray/__init__.py
CDTray/about.py
CDTray/cdtray.pro
CDTray/cdtray.svg
CDTray/config.py
CDTray/player.py
CDTray/sys_notify.py
CDTray/locales/es.qm
CDTray/locales/es.ts
bin/AppRun.sh
bin/cdtray
bin/io.sonlink.cdtray.appdata.xml
bin/io.sonlink.cdtray.desktop
bin/io.sonlink.cdtray.png
bin/io.sonlink.cdtray.svg
cdtray.egg-info/PKG-INFO
cdtray.egg-info/SOURCES.txt
cdtray.egg-info/dependency_links.txt
cdtray.egg-info/requires.txt
cdtray.egg-info/top_level.txt
debian/changelog
debian/compat
debian/control
debian/files
debian/install
debian/rules
debian/data/cdtray.desktop
debian/data/cdtray.svg
packages/aur/PKGBUILD
translate/create_pot.sh
translate/es.po
translate/messages.pot