Metadata-Version: 2.1
Name: cdtray
Version: 2.0rc1
Summary: Play your audio CDs directly from the system tray
Home-page: https://github.com/son-link/CD-Tray
Download-URL: https://github.com/son-link/CD-Tray/archive/refs/tags/v.2.0.rc1.tar.gz
Author: Alfonso Saavedra 'Son Link'
Author-email: sonlink.dourden@gmail.com
License: GPL 3.0
Keywords: music,audio,player
Classifier: Development Status :: 5 - Production/Stable
Classifier: Environment :: X11 Applications :: Qt
Classifier: Topic :: Multimedia :: Sound/Audio
Classifier: Topic :: Multimedia :: Sound/Audio :: Players
Classifier: Topic :: Multimedia :: Sound/Audio :: CD Audio
Classifier: Topic :: Multimedia :: Sound/Audio :: CD Audio :: CD Playing
Classifier: License :: OSI Approved :: GNU General Public License v3 or later (GPLv3+)
Classifier: Programming Language :: Python :: 3
Classifier: Programming Language :: Python :: 3.4
Classifier: Programming Language :: Python :: 3.5
Classifier: Programming Language :: Python :: 3.6
Classifier: Programming Language :: Python :: 3.7
Classifier: Programming Language :: Python :: 3.8
Classifier: Programming Language :: Python :: 3.9
Classifier: Intended Audience :: End Users/Desktop
Classifier: Operating System :: OS Independent
